modelplus/__init__.py
modelplus/apps.py
modelplus/middleware.py
modelplus/models.py
modelplus/py.typed
modelplus/locale/hr/LC_MESSAGES/django.mo
modelplus/locale/hr/LC_MESSAGES/django.po
opensod_modelplus-1.0.0.dist-info/METADATA
opensod_modelplus-1.0.0.dist-info/WHEEL
opensod_modelplus-1.0.0.dist-info/licenses/AUTHORS.md
opensod_modelplus-1.0.0.dist-info/licenses/LICENSE
opensod_modelplus-1.0.0.dist-info/RECORD
